defines.sv
`define READ 0
`define WRITE 1
`define PCR 16 // program counter index
`define tick #1clock=1;#1clock=0
`define dbg

arch-project.srcs/sources_1/imports/cse490-project1/memory.sv
`include "defines.sv"

module memory(
    input reg clock, // read or write
    input reg [15:0] inWord, // word to write
    input int addr, optype, // memory address to access
    output reg [15:0] outWord // read word
);

reg [7:0] memoryArray [0:127] = '{ 
    'h01, 'h20, 'h30, 'h35, 'h60, 'h05, 'h31, 'h40, 'h00, 'h21,
    'h0000, 'h0000, 'h0000, 'h0000, 'h0000,
    'h0000, 'h0000, 'h0000, 'h0000, 'h0000,
    'h0000, 'h0000, 'h0000, 'h0000, 'h0000,
    'h0000, 'h0000, 'h0000, 'h0000, 'h0000,
    'h0000, 'h0000, 'h0000, 'h0000, 'h0000,
    'h0000, 'h0000, 'h0000, 'h0000, 'h0000,
    'h0000, 'h0000, 'h0000, 'h0000, 'h0000,
    'h0000, 'h0000, 'h0000, 'h0000, 'h0000,
    'h0000, 'h0000, 'h0000, 'h0000, 'h0000,
    'h0000, 'h0000, 'h0000, 'h0000, 'h0000,
    'h0000, 'h0000, 'h0000, 'h0000, 'h0000,
    'h0000, 'h0000, 'h0000, 'h0000, 'h0000,
    'h0000, 'h0000, 'h0000, 'h0000, 'h0000,
    'h0000, 'h0000, 'h0000, 'h0000, 'h0000,
    'h0000, 'h0000, 'h0000, 'h0000, 'h0000,
    'h0000, 'h0000, 'h0000, 'h0000, 'h0000,
    'h0000, 'h0000, 'h0000, 'h0000, 'h0000,
    'h0000, 'h0000, 'h0000, 'h0000, 'h0000,
    'h0000, 'h0000, 'h0000, 'h0000, 'h0000,
    'h0000, 'h0000, 'h0000, 'h0000, 'h0000,
    'h0000, 'h0000, 'h0000, 'h0000, 'h0000,
    'h0000, 'h0000, 'h0000, 'h0000, 'h0000,
    'h0000, 'h0000, 'h0000, 'h0000, 'h0000,
    'h0000, 'h0000, 'h0000
};


    `ifdef dbg
    reg [7:0] temp1 ='h0;
    reg [7:0] temp2 ='h0;
    `endif

    always_comb begin
//        $readmemh("memory.mem", memoryArray, 0, 127); // initialize memory into array
//        $stop();
        if (optype == `READ) begin
          `ifdef dbg
          $display("[debug:memory] operation is READ, time=%1d", $time);
          temp1 = memoryArray[addr];
          temp2 = memoryArray[addr+1];
          `endif
          outWord[7:0]  = memoryArray[addr+1]; // don't need to validate reading, read lower word
          outWord[15:8] = memoryArray[addr];
          `ifdef dbg
            $display("[debug:memory] outWord = %4h", outWord);
          `endif
        end 
        
        if (optype == `WRITE) begin
            // ASSUMING WRITE
            $display("[debug:memory] operation is WRITE");
            // it makes sense to nest here
            if (addr > 'h3F) begin // write operations are only valid from 0x40 to 0x7F, 0x0 to 0x3F are read-only
              memoryArray[addr] = inWord[7:0];
              memoryArray[addr+1] = inWord[15:8]; // write upper word
              `ifdef dbg

              temp1 = memoryArray[addr];
              temp2 = memoryArray[addr+1];
              $display("[debug:memory] addr=0x%2h, addr+1=0x%2h, temp1=0x%2h, temp2=0x%2h", addr, addr+1, temp1, temp2);
              `endif
              $writememh("memory.mem", memoryArray, 0, 127); // can only write entire contents of memory, not individual bytes
              // return input word as output
              outWord = inWord;
            end else begin
              // if addr is not more than 0x3F then we're trying to write to
              // read-only memory, return null vector
              outWord = 16'h0; 
            end

        end

    end



endmodule

arch-project.srcs/sources_1/imports/cse490-project1/reg.sv
`include "defines.sv"

module register (
    input reg [15:0] incomingData,
    input int index, accessType,
    input logic clk,
    output logic [15:0] outgoingData
);

// outgoing data on write will just be the data given
reg [15:0] registers [17] = '{default: 'h0}; // 17 registers, r16 is pc

always_comb begin
    if (accessType == `WRITE) begin

        outgoingData = incomingData;
        registers[index] = incomingData; // writes the new data to the indexed register

    end  else if (accessType == `READ) 

        outgoingData = registers[index];

    else begin

        outgoingData = 'h0000; // null on invalid access type 
        $display("Invalid register access type");

    end
//    $writememh("regs.mem", registers, 0, 16);
end

endmodule

pc.sv
// IMPORTANT: read section 5.4.3 – Detailed Instruction Information
module ProgramCounter(
  input logic clock,				    // input clock - not really using anymore
  input int pc_current,	    // previous pc, needs to be incremented by 2
  input logic flag_branch,			    // branch flag from control unit
  input logic flag_branch_select,       // Extra control code to select between BNE or BEQ logic. If branch_select is 0, select BEQ logic. If 1, select BNE logic
  input logic aluZero,				    // zero output from ALU
  input logic flag_jump, 			    // jump flag from control unit
  input logic [15:0] fullInstr,		    // 16-bit decoded instruction from instruction memory Used for the branch offset and jump address calculations.
  output int pc_next		    // next address to send to the instruction memory on next clock cycle
);
  
  // Declare all variables outside of always block
  int nextAddr;
  int branchAddr;
  int signExtImm;
  logic beq_logic, bne_logic, branchMux;
  int pcSrc;
  int jumpAddr;
  
  // * A clocked pc will introduce a delay because it will want to run on posedge of the clock using the previous cycle fetched instruction.
  //   This would only be a problem when the previous instruction was a jump or taken branch instruction.
  //   That would invalidate this cycle's next address but still compute and write based on the instruction.
  //   THAT IS WHY THEY SAY TO PUT NOPs AFTER A BRANCH OR JUMP INSTRUCTION!!!!
  //   (we really only NEED a clocked pc if the datapath is pipelined where pc needs to run every posedge of the clock) 
    always_comb begin
    // Increment pc to get next instruction address.
    nextAddr = pc_current + 2;

    // Calculate the full branch address from the last 4-bits of instruction - 4-bit signed immediate. 
    signExtImm = {{12{fullInstr[3]}}, fullInstr[3:0]};	// sign extend 4-bit immediate
    branchAddr = nextAddr + (signExtImm << 1);	// (pc+2) + (sign-extended imm * 2) 
    
    // Branch instruction MUX logic.
    beq_logic = flag_branch & aluZero;
    bne_logic = flag_branch & ~aluZero;
    branchMux = (flag_branch_select) ? bne_logic : beq_logic;  // If flag_branch_select is 1, select BNE logic. If 0, select BEQ logic.
    pcSrc = (branchMux) ? branchAddr : nextAddr;  // If branchMUX is 1, select branchAddr. If 0, select pc + 2.
    
    // Calculate full jump address by adding pc+2 and (12-bit jump address * 2)
    // to make the 16-bit jump address
    jumpAddr = nextAddr + (fullInstr[11:0] << 1);

    // Jump instruction MUX logic. If 1, select jumpAddr. If 0, select result from branch MUX.
    // Update program counter ouput
    pc_next = (flag_jump) ? jumpAddr : pcSrc;

    
    // DEBUG - comment out if u dont want it
//    $display("[PC MODULE @ %0t] pc_current=%h, nextAddr=%h, fullInstr=%h, signExtImm=%h, branchAddr=%h, pcSrc = %h, jumpAddr=%h, flag_jump=%h, pc_next=%h",
//            $time, pc_current, nextAddr, fullInstr, signExtImm, branchAddr, pcSrc, jumpAddr, flag_jump, pc_next);
  end
  
endmodule

arch-project.srcs/sim_1/new/testbench.sv
`include "defines.sv"
`timescale 1ns/1ns
// testbench to run everything, make sure that things make sense
module tb;
    reg [15:0] reg_write = 'h0000; // write to register
    reg [15:0] mem_write = 'h0000; // the thing to write to memory

    logic [15:0] reg_result = 'h0; // result of the tested operation
    logic [15:0] mem_result = 'h0;

    int idx = 3; // index value of the registers
    logic clock = 0; // clock
    int reg_operation_type = `WRITE; // type of operation for registers
    int mem_operation_type = `READ; // type of operation for memory
    int addr = 'h0;
    
    int current_address = 0;
    int next_address = 0;
    logic [15:0] instruction = 'h0;
    logic branch_flag = 0;
    logic branch_select_flag = 0;
    logic alu_zero_flag = 0;
    logic jump_flag = 0;
    
    

    ProgramCounter pc
    (
        .clock(clock),
        .pc_current(current_address),
        .flag_branch(branch_flag),
        .flag_branch_select(branch_select_flag),
        .aluZero(alu_zero_flag),
        .flag_jump(jump_flag),
        .pc_next(next_address),
        .fullInstr(instruction)
    );

    register ra
    (
        .index(idx),
        .accessType(reg_operation_type),
        .clk(clock),
        .incomingData(reg_write),
        .outgoingData(reg_result)
    );

     memory mem(
    
       .clock(clock),
       .inWord(mem_write),
       .outWord(mem_result),
       .addr(addr),
       .optype(mem_operation_type)
     );
    
    

    initial begin

        $dumpfile("tb.vcd");
        $dumpvars(1); // dumpvars  
//        $monitor("reg_write = %4h, mem_write = %4h, reg idx = %2d, current_address = %2d, next_address = %2d, addr = %2d, time = %2d", reg_write, mem_write, idx, current_address, next_address, addr, $time);
        #120 $finish();
    end   

    // pc testbench, integrated with register and memory
    always begin
        /*
         steps: grab address (current_address) 0 from memory and read it, giving it to pc
         this will be the first instruction read 
         then, starting at current_address 0 it should increment the address by 2
         and store it in the register file
        */
        $stop(); // stop at the beginning of every cycle
        idx = `PCR; // PC register index
        reg_operation_type = `WRITE;
        instruction = mem_result;
        #1 clock = 1;
        #1 clock = 0;
        reg_write = next_address; // update program counter 
        // commmits the write to the pcr
        // now read it
        reg_operation_type = `READ;
        current_address = reg_result; // update program counter's address
        addr = current_address; // get next word
        instruction = mem_result
        
;
    end



endmodule

arch-project.sim/sim_1/behav/xsim/tb.vcd
$date
   Thu Apr 10 23:43:52 2025
$end

$version
  2024.2.2
  $dumpfile ("tb.vcd") 
$end

$timescale
  1ps
$end

$scope module tb $end
$var reg 16 ! reg_write [15:0] $end
$var reg 16 " mem_write [15:0] $end
$var reg 16 # reg_result [15:0] $end
$var reg 16 $ mem_result [15:0] $end
$var reg 32 % idx [31:0] $end
$var reg 1 & clock $end
$var reg 32 ' reg_operation_type [31:0] $end
$var reg 32 ( mem_operation_type [31:0] $end
$var reg 32 ) addr [31:0] $end
$var reg 32 * current_address [31:0] $end
$var reg 32 + next_address [31:0] $end
$var reg 16 , instruction [15:0] $end
$var reg 1 - branch_flag $end
$var reg 1 . branch_select_flag $end
$var reg 1 / alu_zero_flag $end
$var reg 1 0 jump_flag $end
$upscope $end
$scope module glbl $end
$upscope $end
$enddefinitions $end

#0
$dumpvars
b0 !
b0 "
b0 #
b100100000 $
b10000 %
0&
b1 '
b0 (
b0 )
b0 *
b0 +
b0 ,
0-
0.
0/
00
$end

#1000
1&
b10 +

#2000
b10 !
b10 #
0&
b1 '
b100100000 ,

#3000
1&

#4000
b11000000110101 $
0&
b1 '
b10 )
b10 *

#5000
1&
b100 +

#6000
b100 !
b100 #
0&
b1 '
b11000000110101 ,

#7000
1&

#8000
b110000000000101 $
0&
b1 '
b100 )
b100 *

#9000
1&
b110 +

#10000
b110 !
b110 #
0&
b1 '
b110000000000101 ,

#11000
1&

#12000
b11000101000000 $
0&
b1 '
b110 )
b110 *

#13000
1&
b1000 +

#14000
b1000 !
b1000 #
0&
b1 '
b11000101000000 ,

#15000
1&

#16000
b100001 $
0&
b1 '
b1000 )
b1000 *

#17000
1&
b1010 +

#18000
b1010 !
b1010 #
0&
b1 '
b100001 ,

#19000
1&

#20000
b0 $
0&
b1 '
b1010 )
b1010 *

#21000
1&
b1100 +

#22000
b1100 !
0&
b0 '
b0 ,
